typedenv/__init__.py
typedenv/_internals.py
typedenv/annotations.py
typedenv/converters.py
typedenv/loader.py
typedenv/py.typed
typedenv_py-1.0.1.dist-info/LICENSE
typedenv_py-1.0.1.dist-info/METADATA
typedenv_py-1.0.1.dist-info/WHEEL
typedenv_py-1.0.1.dist-info/RECORD
