Metadata-Version: 2.1
Name: typedenv.py
Version: 1.0.1
Summary: Load environment variables with class type hints
Home-page: https://github.com/ShajeshJ/typedenv.py
License: MIT
Author: Shajesh Jegatheeswaran
Author-email: shajesh.14@gmail.com
Requires-Python: >=3.10,<4.0
Classifier: License :: OSI Approved :: MIT License
Classifier: Programming Language :: Python :: 3
Classifier: Programming Language :: Python :: 3.10
Classifier: Programming Language :: Python :: 3.11
Classifier: Programming Language :: Python :: 3.12
Classifier: Topic :: Software Development :: Libraries :: Python Modules
Classifier: Typing :: Typed
Project-URL: Repository, https://github.com/ShajeshJ/typedenv.py
